LOVELY/STRUCTURES/CYTE/ELECTRIC_CURRENT/ELECTRIC_CURRENT.HTML
LOVELY/STRUCTURES/CYTE/ENERGY/ENERGY.HTML
LOVELY/STRUCTURES/CYTE/FOOD/FOOD FOR BABIES.HTML
LOVELY/STRUCTURES/CYTE/FOOD/FOOD.CONCEPTABILITY.HTML
LOVELY/STRUCTURES/CYTE/FOOD/FOOD.VEGAN.CONCEPTABILITY.HTML
LOVELY/STRUCTURES/CYTE/FOOD/USDA/API/ONE/ASSERTIONS/BRANDED.py
LOVELY/STRUCTURES/CYTE/FOOD/USDA/API/ONE/ASSERTIONS/FOUNDATIONAL.py
LOVELY/STRUCTURES/CYTE/FOOD/USDA/API/ONE/STATUS/API_STATUS_1.py
LOVELY/STRUCTURES/CYTE/FOOD/USDA/API/ONE/__init__.py
LOVELY/STRUCTURES/CYTE/FOOD/USDA/EXAMPLES/BRANDED/BEET_JUICE_2642759.JSON
LOVELY/STRUCTURES/CYTE/FOOD/USDA/EXAMPLES/BRANDED/IMPOSSIBLE_2468423.JSON
LOVELY/STRUCTURES/CYTE/FOOD/USDA/EXAMPLES/FOUNDATIONAL/2346404_SWEET_POTATOES.JSON
LOVELY/STRUCTURES/CYTE/FOOD/USDA/FORM_1/STATUS/STATUS_1.py
LOVELY/STRUCTURES/CYTE/FOOD/USDA/FORM_1/__init__.py
LOVELY/STRUCTURES/CYTE/FOOD/USDA/PROCESS/INGREDIENTS/__init__.py
LOVELY/STRUCTURES/CYTE/FOOD/USDA/PROCESS/PACKAGE_MASS/__init__.py
LOVELY/STRUCTURES/CYTE/FOOD/USDA/PROCESS/STRUCTURE_MASS/STATUS_1.py
LOVELY/STRUCTURES/CYTE/FOOD/USDA/PROCESS/STRUCTURE_MASS/__init__.py
LOVELY/STRUCTURES/CYTE/FOOD/USDA/PROCESS/__init__.py
LOVELY/STRUCTURES/CYTE/LENGTH/LENGTH.HTML
LOVELY/STRUCTURES/CYTE/MASS/E_NOTE.py
"LOVELY/STRUCTURES/CYTE/MASS/MASS, SYSTEM INTERNATION.HTML"
"LOVELY/STRUCTURES/CYTE/MASS/MASS, US CUSTOMARY UNITS.HTML"
LOVELY/STRUCTURES/CYTE/MASS/MASS.HTML
LOVELY/STRUCTURES/CYTE/MASS/SWAP/STATUS_1.py
LOVELY/STRUCTURES/CYTE/MASS/SWAP/__init__.py
LOVELY/STRUCTURES/CYTE/STRUCTS/DB/ACCESS.py
LOVELY/STRUCTURES/CYTE/STRUCTS/DB/PATH.py
LOVELY/STRUCTURES/CYTE/STRUCTS/DB/STRUCTS.JSON
LOVELY/STRUCTURES/CYTE/STRUCTS/FIND.py
LOVELY/STRUCTURES/CYTE/STRUCTS/INSERT.py
LOVELY/STRUCTURES/CYTE/STRUCTS/INSERT_LIST.py
LOVELY/STRUCTURES/CYTE/STRUCTS/LIST.py
LOVELY/STRUCTURES/CYTE/STRUCTS/_STRUCTS.HTML
LOVELY/STRUCTURES/CYTE/TEMPERATURE/TEMPERATURE.HTML
LOVELY/STRUCTURES/CYTE/VOLUME/VOLUME.HTML
LOVELY/STRUCTURES/CYTE/WEIGHT/CONVERT.py
LOVELY/STRUCTURES/CYTE.egg-info/PKG-INFO
LOVELY/STRUCTURES/CYTE.egg-info/SOURCES.txt
LOVELY/STRUCTURES/CYTE.egg-info/dependency_links.txt
LOVELY/STRUCTURES/CYTE.egg-info/top_level.txt
cyte-0.0.5.dist-info/METADATA
cyte-0.0.5.dist-info/WHEEL
cyte-0.0.5.dist-info/RECORD
