Metadata-Version: 2.1
Name: cyte
Version: 0.0.5
Summary: 
License: THL
Author: Bryan Grace
Requires-Python: >=3.11,<4.0
Classifier: License :: Other/Proprietary License
Classifier: Programming Language :: Python :: 3
Classifier: Programming Language :: Python :: 3.11
Requires-Dist: tinydb (>=4.8.0,<5.0.0)
